[
    {
        "model": "workup.clinicdate",
        "pk": 1,
        "fields": {
            "clinic_type": 4,
            "clinic_date": "2019-09-10"
        }
    },
    {
        "model": "users.user",
        "pk": 1,
        "fields": {
            "name": "Annie Attending",
            "phone": "555-233-1234",
            "languages": [
                "English"
            ],
            "gender": "Female",
            "needs_updating": false
        }
    },
    {
        "model": "auth.group",
        "pk": 1,
        "fields": {
            "name": "foo"
        }
    },
    {
        "model": "demographics.chroniccondition",
        "pk": 1,
        "fields": {
            "name": "hypertension"
        }
    },
    {
        "model": "demographics.demographics",
        "pk": 1,
        "fields": {
            "patient": 1,
            "chronic_conditions": [
                "hypertension"
            ]
        }
    },
    {
        "model": "workup.workup",
        "pk": 1,
        "fields": {
            "clinic_day": 1,
            "chief_complaint": "SOB",
            "diagnosis": "MI",
            "hpi": "abc",
            "pmh": "abc",
            "meds": "abc",
            "allergies": "abc",
            "fam_hx": "abc",
            "soc_hx": "abc",
            "ros": "f",
            "pe": "f",
            "a_and_p": "f",
            "hr": "89",
            "bp_sys": "120",
            "bp_dia": "80",
            "rr": "16",
            "t": "98",
            "labs_ordered_internal": "f",
            "got_voucher": false,
            "got_imaging_voucher": false,
            "will_return": true,
            "author": 1,
            "author_type": 1,
            "patient": 1,
            "written_datetime": "2019-09-10",
            "last_modified": "2019-09-10"
        }
    },
    {
        "model": "workup.workup",
        "pk": 4,
        "fields": {
            "clinic_day": 1,
            "chief_complaint": "High BP 3",
            "diagnosis": "hypertension",
            "hpi": "abc",
            "pmh": "abc",
            "meds": "abc",
            "allergies": "abc",
            "fam_hx": "abc",
            "soc_hx": "abc",
            "ros": "f",
            "pe": "f",
            "a_and_p": "f",
            "hr": "89",
            "bp_sys": "170",
            "bp_dia": "80",
            "rr": "16",
            "t": "98",
            "labs_ordered_internal": "f",
            "got_voucher": false,
            "got_imaging_voucher": false,
            "will_return": true,
            "author": 1,
            "author_type": 1,
            "patient": 3,
            "written_datetime": "2019-09-10",
            "last_modified": "2019-09-10"
        }
    },
    {
        "model": "workup.workup",
        "pk": 5,
        "fields": {
            "clinic_day": 1,
            "chief_complaint": "High BP 3",
            "diagnosis": "hypertension",
            "hpi": "abc",
            "pmh": "abc",
            "meds": "abc",
            "allergies": "abc",
            "fam_hx": "abc",
            "soc_hx": "abc",
            "ros": "f",
            "pe": "f",
            "a_and_p": "f",
            "hr": "89",
            "bp_sys": "172",
            "bp_dia": "80",
            "rr": "16",
            "t": "98",
            "labs_ordered_internal": "f",
            "got_voucher": false,
            "got_imaging_voucher": false,
            "will_return": true,
            "author": 1,
            "author_type": 1,
            "patient": 6,
            "written_datetime": "2019-10-21",
            "last_modified": "2019-09-10"
        }
    },
    {
        "model": "workup.workup",
        "pk": 6,
        "fields": {
            "clinic_day": 1,
            "chief_complaint": "High BP 3",
            "diagnosis": "hypertension",
            "hpi": "abc",
            "pmh": "abc",
            "meds": "abc",
            "allergies": "abc",
            "fam_hx": "abc",
            "soc_hx": "abc",
            "ros": "f",
            "pe": "f",
            "a_and_p": "f",
            "hr": "89",
            "bp_sys": "100",
            "bp_dia": "80",
            "rr": "16",
            "t": "98",
            "labs_ordered_internal": "f",
            "got_voucher": false,
            "got_imaging_voucher": false,
            "will_return": true,
            "author": 1,
            "author_type": 1,
            "patient": 6,
            "written_datetime": "2020-05-17",
            "last_modified": "2019-09-10"
        }
    },
    {
        "model": "workup.workup",
        "pk": 7,
        "fields": {
            "clinic_day": 1,
            "chief_complaint": "High BP 3",
            "diagnosis": "hypertension",
            "hpi": "abc",
            "pmh": "abc",
            "meds": "abc",
            "allergies": "abc",
            "fam_hx": "abc",
            "soc_hx": "abc",
            "ros": "f",
            "pe": "f",
            "a_and_p": "f",
            "hr": "89",
            "bp_sys": "158",
            "bp_dia": "80",
            "rr": "16",
            "t": "98",
            "labs_ordered_internal": "f",
            "got_voucher": false,
            "got_imaging_voucher": false,
            "will_return": true,
            "author": 1,
            "author_type": 1,
            "patient": 7,
            "written_datetime": "2020-04-10",
            "last_modified": "2019-09-10"
        }
    },
    {
        "model": "workup.workup",
        "pk": 8,
        "fields": {
            "clinic_day": 1,
            "chief_complaint": "High BP 3",
            "diagnosis": "hypertension",
            "hpi": "abc",
            "pmh": "abc",
            "meds": "abc",
            "allergies": "abc",
            "fam_hx": "abc",
            "soc_hx": "abc",
            "ros": "f",
            "pe": "f",
            "a_and_p": "f",
            "hr": "89",
            "bp_sys": "101",
            "bp_dia": "80",
            "rr": "16",
            "t": "98",
            "labs_ordered_internal": "f",
            "got_voucher": false,
            "got_imaging_voucher": false,
            "will_return": true,
            "author": 1,
            "author_type": 1,
            "patient": 7,
            "written_datetime": "2018-05-26",
            "last_modified": "2019-09-10"
        }
    },
    {
        "model": "workup.workup",
        "pk": 9,
        "fields": {
            "clinic_day": 1,
            "chief_complaint": "High BP 3",
            "diagnosis": "hypertension",
            "hpi": "abc",
            "pmh": "abc",
            "meds": "abc",
            "allergies": "abc",
            "fam_hx": "abc",
            "soc_hx": "abc",
            "ros": "f",
            "pe": "f",
            "a_and_p": "f",
            "hr": "89",
            "bp_sys": "132",
            "bp_dia": "80",
            "rr": "16",
            "t": "98",
            "labs_ordered_internal": "f",
            "got_voucher": false,
            "got_imaging_voucher": false,
            "will_return": true,
            "author": 1,
            "author_type": 1,
            "patient": 7,
            "written_datetime": "2018-08-07",
            "last_modified": "2019-09-10"
        }
    },
    {
        "model": "workup.workup",
        "pk": 10,
        "fields": {
            "clinic_day": 1,
            "chief_complaint": "High BP 3",
            "diagnosis": "hypertension",
            "hpi": "abc",
            "pmh": "abc",
            "meds": "abc",
            "allergies": "abc",
            "fam_hx": "abc",
            "soc_hx": "abc",
            "ros": "f",
            "pe": "f",
            "a_and_p": "f",
            "hr": "89",
            "bp_sys": "107",
            "bp_dia": "80",
            "rr": "16",
            "t": "98",
            "labs_ordered_internal": "f",
            "got_voucher": false,
            "got_imaging_voucher": false,
            "will_return": true,
            "author": 1,
            "author_type": 1,
            "patient": 7,
            "written_datetime": "2020-05-04",
            "last_modified": "2019-09-10"
        }
    },
    {
        "model": "workup.workup",
        "pk": 11,
        "fields": {
            "clinic_day": 1,
            "chief_complaint": "High BP 3",
            "diagnosis": "hypertension",
            "hpi": "abc",
            "pmh": "abc",
            "meds": "abc",
            "allergies": "abc",
            "fam_hx": "abc",
            "soc_hx": "abc",
            "ros": "f",
            "pe": "f",
            "a_and_p": "f",
            "hr": "89",
            "bp_sys": "146",
            "bp_dia": "80",
            "rr": "16",
            "t": "98",
            "labs_ordered_internal": "f",
            "got_voucher": false,
            "got_imaging_voucher": false,
            "will_return": true,
            "author": 1,
            "author_type": 1,
            "patient": 8,
            "written_datetime": "2019-09-19",
            "last_modified": "2019-09-10"
        }
    },
    {
        "model": "workup.workup",
        "pk": 12,
        "fields": {
            "clinic_day": 1,
            "chief_complaint": "High BP 3",
            "diagnosis": "hypertension",
            "hpi": "abc",
            "pmh": "abc",
            "meds": "abc",
            "allergies": "abc",
            "fam_hx": "abc",
            "soc_hx": "abc",
            "ros": "f",
            "pe": "f",
            "a_and_p": "f",
            "hr": "89",
            "bp_sys": "164",
            "bp_dia": "80",
            "rr": "16",
            "t": "98",
            "labs_ordered_internal": "f",
            "got_voucher": false,
            "got_imaging_voucher": false,
            "will_return": true,
            "author": 1,
            "author_type": 1,
            "patient": 9,
            "written_datetime": "2018-01-03",
            "last_modified": "2019-09-10"
        }
    },
    {
        "model": "workup.workup",
        "pk": 13,
        "fields": {
            "clinic_day": 1,
            "chief_complaint": "High BP 3",
            "diagnosis": "hypertension",
            "hpi": "abc",
            "pmh": "abc",
            "meds": "abc",
            "allergies": "abc",
            "fam_hx": "abc",
            "soc_hx": "abc",
            "ros": "f",
            "pe": "f",
            "a_and_p": "f",
            "hr": "89",
            "bp_sys": "160",
            "bp_dia": "80",
            "rr": "16",
            "t": "98",
            "labs_ordered_internal": "f",
            "got_voucher": false,
            "got_imaging_voucher": false,
            "will_return": true,
            "author": 1,
            "author_type": 1,
            "patient": 9,
            "written_datetime": "2019-08-09",
            "last_modified": "2019-09-10"
        }
    },
    {
        "model": "workup.workup",
        "pk": 14,
        "fields": {
            "clinic_day": 1,
            "chief_complaint": "High BP 3",
            "diagnosis": "hypertension",
            "hpi": "abc",
            "pmh": "abc",
            "meds": "abc",
            "allergies": "abc",
            "fam_hx": "abc",
            "soc_hx": "abc",
            "ros": "f",
            "pe": "f",
            "a_and_p": "f",
            "hr": "89",
            "bp_sys": "148",
            "bp_dia": "80",
            "rr": "16",
            "t": "98",
            "labs_ordered_internal": "f",
            "got_voucher": false,
            "got_imaging_voucher": false,
            "will_return": true,
            "author": 1,
            "author_type": 1,
            "patient": 10,
            "written_datetime": "2019-03-04",
            "last_modified": "2019-09-10"
        }
    },
    {
        "model": "workup.workup",
        "pk": 15,
        "fields": {
            "clinic_day": 1,
            "chief_complaint": "High BP 3",
            "diagnosis": "hypertension",
            "hpi": "abc",
            "pmh": "abc",
            "meds": "abc",
            "allergies": "abc",
            "fam_hx": "abc",
            "soc_hx": "abc",
            "ros": "f",
            "pe": "f",
            "a_and_p": "f",
            "hr": "89",
            "bp_sys": "126",
            "bp_dia": "80",
            "rr": "16",
            "t": "98",
            "labs_ordered_internal": "f",
            "got_voucher": false,
            "got_imaging_voucher": false,
            "will_return": true,
            "author": 1,
            "author_type": 1,
            "patient": 11,
            "written_datetime": "2019-05-12",
            "last_modified": "2019-09-10"
        }
    },
    {
        "model": "workup.workup",
        "pk": 16,
        "fields": {
            "clinic_day": 1,
            "chief_complaint": "High BP 3",
            "diagnosis": "hypertension",
            "hpi": "abc",
            "pmh": "abc",
            "meds": "abc",
            "allergies": "abc",
            "fam_hx": "abc",
            "soc_hx": "abc",
            "ros": "f",
            "pe": "f",
            "a_and_p": "f",
            "hr": "89",
            "bp_sys": "138",
            "bp_dia": "80",
            "rr": "16",
            "t": "98",
            "labs_ordered_internal": "f",
            "got_voucher": false,
            "got_imaging_voucher": false,
            "will_return": true,
            "author": 1,
            "author_type": 1,
            "patient": 11,
            "written_datetime": "2019-07-16",
            "last_modified": "2019-09-10"
        }
    },
    {
        "model": "workup.workup",
        "pk": 17,
        "fields": {
            "clinic_day": 1,
            "chief_complaint": "High BP 3",
            "diagnosis": "hypertension",
            "hpi": "abc",
            "pmh": "abc",
            "meds": "abc",
            "allergies": "abc",
            "fam_hx": "abc",
            "soc_hx": "abc",
            "ros": "f",
            "pe": "f",
            "a_and_p": "f",
            "hr": "89",
            "bp_sys": "141",
            "bp_dia": "80",
            "rr": "16",
            "t": "98",
            "labs_ordered_internal": "f",
            "got_voucher": false,
            "got_imaging_voucher": false,
            "will_return": true,
            "author": 1,
            "author_type": 1,
            "patient": 11,
            "written_datetime": "2018-08-10",
            "last_modified": "2019-09-10"
        }
    },
    {
        "model": "workup.workup",
        "pk": 18,
        "fields": {
            "clinic_day": 1,
            "chief_complaint": "High BP 3",
            "diagnosis": "hypertension",
            "hpi": "abc",
            "pmh": "abc",
            "meds": "abc",
            "allergies": "abc",
            "fam_hx": "abc",
            "soc_hx": "abc",
            "ros": "f",
            "pe": "f",
            "a_and_p": "f",
            "hr": "89",
            "bp_sys": "155",
            "bp_dia": "80",
            "rr": "16",
            "t": "98",
            "labs_ordered_internal": "f",
            "got_voucher": false,
            "got_imaging_voucher": false,
            "will_return": true,
            "author": 1,
            "author_type": 1,
            "patient": 11,
            "written_datetime": "2020-08-20",
            "last_modified": "2019-09-10"
        }
    },
    {
        "model": "workup.workup",
        "pk": 19,
        "fields": {
            "clinic_day": 1,
            "chief_complaint": "High BP 3",
            "diagnosis": "hypertension",
            "hpi": "abc",
            "pmh": "abc",
            "meds": "abc",
            "allergies": "abc",
            "fam_hx": "abc",
            "soc_hx": "abc",
            "ros": "f",
            "pe": "f",
            "a_and_p": "f",
            "hr": "89",
            "bp_sys": "121",
            "bp_dia": "80",
            "rr": "16",
            "t": "98",
            "labs_ordered_internal": "f",
            "got_voucher": false,
            "got_imaging_voucher": false,
            "will_return": true,
            "author": 1,
            "author_type": 1,
            "patient": 11,
            "written_datetime": "2019-09-21",
            "last_modified": "2019-09-10"
        }
    },
    {
        "model": "workup.workup",
        "pk": 20,
        "fields": {
            "clinic_day": 1,
            "chief_complaint": "High BP 3",
            "diagnosis": "hypertension",
            "hpi": "abc",
            "pmh": "abc",
            "meds": "abc",
            "allergies": "abc",
            "fam_hx": "abc",
            "soc_hx": "abc",
            "ros": "f",
            "pe": "f",
            "a_and_p": "f",
            "hr": "89",
            "bp_sys": "138",
            "bp_dia": "80",
            "rr": "16",
            "t": "98",
            "labs_ordered_internal": "f",
            "got_voucher": false,
            "got_imaging_voucher": false,
            "will_return": true,
            "author": 1,
            "author_type": 1,
            "patient": 12,
            "written_datetime": "2020-03-04",
            "last_modified": "2019-09-10"
        }
    },
    {
        "model": "workup.workup",
        "pk": 21,
        "fields": {
            "clinic_day": 1,
            "chief_complaint": "High BP 3",
            "diagnosis": "hypertension",
            "hpi": "abc",
            "pmh": "abc",
            "meds": "abc",
            "allergies": "abc",
            "fam_hx": "abc",
            "soc_hx": "abc",
            "ros": "f",
            "pe": "f",
            "a_and_p": "f",
            "hr": "89",
            "bp_sys": "118",
            "bp_dia": "80",
            "rr": "16",
            "t": "98",
            "labs_ordered_internal": "f",
            "got_voucher": false,
            "got_imaging_voucher": false,
            "will_return": true,
            "author": 1,
            "author_type": 1,
            "patient": 12,
            "written_datetime": "2019-04-13",
            "last_modified": "2019-09-10"
        }
    },
    {
        "model": "workup.workup",
        "pk": 22,
        "fields": {
            "clinic_day": 1,
            "chief_complaint": "High BP 3",
            "diagnosis": "hypertension",
            "hpi": "abc",
            "pmh": "abc",
            "meds": "abc",
            "allergies": "abc",
            "fam_hx": "abc",
            "soc_hx": "abc",
            "ros": "f",
            "pe": "f",
            "a_and_p": "f",
            "hr": "89",
            "bp_sys": "152",
            "bp_dia": "80",
            "rr": "16",
            "t": "98",
            "labs_ordered_internal": "f",
            "got_voucher": false,
            "got_imaging_voucher": false,
            "will_return": true,
            "author": 1,
            "author_type": 1,
            "patient": 12,
            "written_datetime": "2018-05-17",
            "last_modified": "2019-09-10"
        }
    },
    {
        "model": "workup.workup",
        "pk": 23,
        "fields": {
            "clinic_day": 1,
            "chief_complaint": "High BP 3",
            "diagnosis": "hypertension",
            "hpi": "abc",
            "pmh": "abc",
            "meds": "abc",
            "allergies": "abc",
            "fam_hx": "abc",
            "soc_hx": "abc",
            "ros": "f",
            "pe": "f",
            "a_and_p": "f",
            "hr": "89",
            "bp_sys": "155",
            "bp_dia": "80",
            "rr": "16",
            "t": "98",
            "labs_ordered_internal": "f",
            "got_voucher": false,
            "got_imaging_voucher": false,
            "will_return": true,
            "author": 1,
            "author_type": 1,
            "patient": 12,
            "written_datetime": "2020-09-15",
            "last_modified": "2019-09-10"
        }
    },
    {
        "model": "workup.workup",
        "pk": 24,
        "fields": {
            "clinic_day": 1,
            "chief_complaint": "High BP 3",
            "diagnosis": "hypertension",
            "hpi": "abc",
            "pmh": "abc",
            "meds": "abc",
            "allergies": "abc",
            "fam_hx": "abc",
            "soc_hx": "abc",
            "ros": "f",
            "pe": "f",
            "a_and_p": "f",
            "hr": "89",
            "bp_sys": "180",
            "bp_dia": "80",
            "rr": "16",
            "t": "98",
            "labs_ordered_internal": "f",
            "got_voucher": false,
            "got_imaging_voucher": false,
            "will_return": true,
            "author": 1,
            "author_type": 1,
            "patient": 12,
            "written_datetime": "2018-06-30",
            "last_modified": "2019-09-10"
        }
    },
    {
        "model": "workup.workup",
        "pk": 25,
        "fields": {
            "clinic_day": 1,
            "chief_complaint": "High BP 3",
            "diagnosis": "hypertension",
            "hpi": "abc",
            "pmh": "abc",
            "meds": "abc",
            "allergies": "abc",
            "fam_hx": "abc",
            "soc_hx": "abc",
            "ros": "f",
            "pe": "f",
            "a_and_p": "f",
            "hr": "89",
            "bp_sys": "155",
            "bp_dia": "80",
            "rr": "16",
            "t": "98",
            "labs_ordered_internal": "f",
            "got_voucher": false,
            "got_imaging_voucher": false,
            "will_return": true,
            "author": 1,
            "author_type": 1,
            "patient": 13,
            "written_datetime": "2019-03-15",
            "last_modified": "2019-09-10"
        }
    },
    {
        "model": "workup.workup",
        "pk": 26,
        "fields": {
            "clinic_day": 1,
            "chief_complaint": "High BP 3",
            "diagnosis": "hypertension",
            "hpi": "abc",
            "pmh": "abc",
            "meds": "abc",
            "allergies": "abc",
            "fam_hx": "abc",
            "soc_hx": "abc",
            "ros": "f",
            "pe": "f",
            "a_and_p": "f",
            "hr": "89",
            "bp_sys": "161",
            "bp_dia": "80",
            "rr": "16",
            "t": "98",
            "labs_ordered_internal": "f",
            "got_voucher": false,
            "got_imaging_voucher": false,
            "will_return": true,
            "author": 1,
            "author_type": 1,
            "patient": 14,
            "written_datetime": "2019-03-03",
            "last_modified": "2019-09-10"
        }
    },
    {
        "model": "workup.workup",
        "pk": 27,
        "fields": {
            "clinic_day": 1,
            "chief_complaint": "High BP 3",
            "diagnosis": "hypertension",
            "hpi": "abc",
            "pmh": "abc",
            "meds": "abc",
            "allergies": "abc",
            "fam_hx": "abc",
            "soc_hx": "abc",
            "ros": "f",
            "pe": "f",
            "a_and_p": "f",
            "hr": "89",
            "bp_sys": "115",
            "bp_dia": "80",
            "rr": "16",
            "t": "98",
            "labs_ordered_internal": "f",
            "got_voucher": false,
            "got_imaging_voucher": false,
            "will_return": true,
            "author": 1,
            "author_type": 1,
            "patient": 14,
            "written_datetime": "2018-05-06",
            "last_modified": "2019-09-10"
        }
    },
    {
        "model": "workup.workup",
        "pk": 28,
        "fields": {
            "clinic_day": 1,
            "chief_complaint": "High BP 3",
            "diagnosis": "hypertension",
            "hpi": "abc",
            "pmh": "abc",
            "meds": "abc",
            "allergies": "abc",
            "fam_hx": "abc",
            "soc_hx": "abc",
            "ros": "f",
            "pe": "f",
            "a_and_p": "f",
            "hr": "89",
            "bp_sys": "109",
            "bp_dia": "80",
            "rr": "16",
            "t": "98",
            "labs_ordered_internal": "f",
            "got_voucher": false,
            "got_imaging_voucher": false,
            "will_return": true,
            "author": 1,
            "author_type": 1,
            "patient": 14,
            "written_datetime": "2018-08-24",
            "last_modified": "2019-09-10"
        }
    }
]